{
  "questionId": "217",
  "title": "Contains Duplicate",
  "titleSlug": "contains-duplicate",
  "difficulty": "Easy",
  "topicTags": [
    {
      "name": "Array",
      "slug": "array"
    },
    {
      "name": "Hash Table",
      "slug": "hash-table"
    },
    {
      "name": "Sorting",
      "slug": "sorting"
    }
  ],
  "content": "Given an integer array nums, return true if any value appears at least twice in the array, and return false if every element is distinct.\n\nExample 1:\n\nInput: nums = [1,2,3,1]\n\nOutput: true\n\nExplanation: The element 1 occurs at the indices 0 and 3.\n\nExample 2:\n\nInput: nums = [1,2,3,4]\n\nOutput: false\n\nExplanation: All elements are distinct.\n\nExample 3:\n\nInput: nums = [1,1,1,3,3,4,3,2,4,2]\n\nOutput: true\n\nConstraints:\n\n• 1 <= nums.length <= 105\n\n• -109 <= nums[i] <= 109",
  "codeSnippets": [
    {
      "lang": "Python",
      "langSlug": "python",
      "code": "class Solution(object):\n    def containsDuplicate(self, nums):\n        \"\"\"\n        :type nums: List[int]\n        :rtype: bool\n        \"\"\"\n        "
    }
  ],
  "hints": [],
  "testCases": [
    [
      "[1,2,3,1]"
    ],
    [
      "[1,2,3,4]"
    ],
    [
      "[1,1,1,3,3,4,3,2,4,2]"
    ]
  ],
  "expectedOutputs": [
    "true",
    "false",
    "true"
  ],
  "has_solutions": true,
  "solutions": {
    "python": "def containsDuplicate(nums):\n    return len(nums) != len(set(nums))",
    "explanation": "The algorithm starts by creating an empty set. Then it iterates through the input array. For each number in the array, it checks if the number is already in the set. If the number is in the set, it means there's a duplicate, so it returns true. If the number is not in the set, it adds the number to the set. If the function has not returned true after iterating through the entire array, it means that there are no duplicates, so it returns false.\n\nIn Python, we use the fact that sets don't allow duplicates, so we can directly compare the length of the original list with the length of the set created from the list. If they are not equal, it means there are duplicates in the list, and the function returns true. Otherwise, it returns false."
  },
  "similarQuestions": "[{\"title\": \"Contains Duplicate II\", \"titleSlug\": \"contains-duplicate-ii\", \"difficulty\": \"Easy\"}, {\"title\": \"Contains Duplicate III\", \"titleSlug\": \"contains-duplicate-iii\", \"difficulty\": \"Hard\"}, {\"title\": \"Make Array Zero by Subtracting Equal Amounts\", \"titleSlug\": \"make-array-zero-by-subtracting-equal-amounts\", \"difficulty\": \"Easy\"}, {\"title\": \"Find Valid Pair of Adjacent Digits in String\", \"titleSlug\": \"find-valid-pair-of-adjacent-digits-in-string\", \"difficulty\": \"Easy\"}]"
}